{
    "InternalName": "Kameck",
    "ClassName": "Kameck",
    "Name": "Magikoopa",
    "List": "ObjectList",
    "Category": "enemy",
    "Description": "A Koopa wizard that can cast spells. Kinda dangerous as it's difficult to defeat it.",
    "Properties": {
        "NearestPoint": "Boolean",
        "PlayerSearchOffsetY": "Single",
        "SearchRange": "Int32",
        "UsingDepthShadow": "Boolean"
    },
    "Models": [],
    "Links": [
        "Rail",
        "SwitchAppear",
        "SwitchKill"
    ]
}